odoo/addons/web_ir_actions_act_window_page/README.rst
odoo/addons/web_ir_actions_act_window_page/__init__.py
odoo/addons/web_ir_actions_act_window_page/__manifest__.py
odoo/addons/web_ir_actions_act_window_page/demo/demo_action.xml
odoo/addons/web_ir_actions_act_window_page/i18n/de.po
odoo/addons/web_ir_actions_act_window_page/i18n/es.po
odoo/addons/web_ir_actions_act_window_page/i18n/it.po
odoo/addons/web_ir_actions_act_window_page/i18n/web_ir_actions_act_window_page.pot
odoo/addons/web_ir_actions_act_window_page/models/__init__.py
odoo/addons/web_ir_actions_act_window_page/models/ir_actions_act_window_page.py
odoo/addons/web_ir_actions_act_window_page/readme/CONTRIBUTORS.rst
odoo/addons/web_ir_actions_act_window_page/readme/DESCRIPTION.rst
odoo/addons/web_ir_actions_act_window_page/readme/USAGE.rst
odoo/addons/web_ir_actions_act_window_page/static/description/icon.png
odoo/addons/web_ir_actions_act_window_page/static/description/index.html
odoo/addons/web_ir_actions_act_window_page/static/src/web_ir_actions_act_window_page.esm.js
odoo_addon_web_ir_actions_act_window_page-16.0.1.0.0.9.dist-info/METADATA
odoo_addon_web_ir_actions_act_window_page-16.0.1.0.0.9.dist-info/WHEEL
odoo_addon_web_ir_actions_act_window_page-16.0.1.0.0.9.dist-info/top_level.txt
odoo_addon_web_ir_actions_act_window_page-16.0.1.0.0.9.dist-info/RECORD
