Metadata-Version: 2.1
Name: odoo-addon-web_ir_actions_act_window_page
Version: 16.0.1.0.0.9
Summary: Allows a developer to trigger a pager to show the previous or next next record in the form view
Home-page: https://github.com/OCA/web
Author: Hunki Enterprises BV, Therp BV,Odoo Community Association (OCA)
Author-email: support@odoo-community.org
License: AGPL-3
Classifier: Programming Language :: Python
Classifier: Framework :: Odoo
Classifier: Framework :: Odoo :: 16.0
Classifier: License :: OSI Approved :: GNU Affero General Public License v3
Requires-Python: >=3.10
Requires-Dist: odoo<16.1dev,>=16.0a
